setup.py
exam_aiml/__init__.py
exam_aiml/exam_aiml.py
exam_aiml.egg-info/PKG-INFO
exam_aiml.egg-info/SOURCES.txt
exam_aiml.egg-info/dependency_links.txt
exam_aiml.egg-info/not-zip-safe
exam_aiml.egg-info/top_level.txt