Metadata-Version: 2.1
Name: exam-aiml
Version: 0.1
Summary: Some aiml programs
Author: RSKN
